typedargparse.py
typedargparse-0.0.1.dist-info/DESCRIPTION.rst
typedargparse-0.0.1.dist-info/METADATA
typedargparse-0.0.1.dist-info/RECORD
typedargparse-0.0.1.dist-info/WHEEL
typedargparse-0.0.1.dist-info/metadata.json
typedargparse-0.0.1.dist-info/top_level.txt
