Metadata-Version: 2.0
Name: typedargparse
Version: 0.0.1
Summary: Simple argparse wrapper with typing
Home-page: https://github.com/emakryo/typedargparse
Author: Ryosuke Kamesawa
Author-email: emak.ryo@gmail.com
License: UNKNOWN
Platform: UNKNOWN
Requires-Python: >=3.5
